balancr/__init__.py
balancr/base.py
balancr/classifier_registry.py
balancr/imbalance_analyser.py
balancr/technique_registry.py
balancr/cli/__init__.py
balancr/cli/commands.py
balancr/cli/config.py
balancr/cli/main.py
balancr/cli/utils.py
balancr/data/__init__.py
balancr/data/loader.py
balancr/data/preprocessor.py
balancr/evaluation/__init__.py
balancr/evaluation/metrics.py
balancr/evaluation/visualisation.py
balancr/techniques/__init__.py
balancr/techniques/custom/__init__.py
balancr/techniques/custom/example_custom_technique.py
balancr-0.1.1.dist-info/licenses/LICENSE
balancr-0.1.1.dist-info/METADATA
balancr-0.1.1.dist-info/WHEEL
balancr-0.1.1.dist-info/entry_points.txt
balancr-0.1.1.dist-info/top_level.txt
balancr-0.1.1.dist-info/RECORD
