Metadata-Version: 2.4
Name: balancr
Version: 0.1.1
Summary: A unified framework for analysing and comparing techniques for handling imbalanced datasets
Home-page: https://github.com/Ruaskill/balancr
Author: Conor Doherty
Author-email: ruaskillz1@gmail.com
License: MIT
Project-URL: Documentation, https://github.com/Ruaskill/balancr/blob/main/README.md
Project-URL: Source, https://github.com/Ruaskill/balancr
Project-URL: Issues, https://github.com/Ruaskill/balancr/issues
Keywords: machine learning,imbalanced data,data balancing,classification,resampling,oversampling,undersampling,SMOTE,ADASYN,imbalanced learning
Classifier: Development Status :: 4 - Beta
Classifier: Intended Audience :: Science/Research
Classifier: Intended Audience :: Developers
Classifier: License :: OSI Approved :: MIT License
Classifier: Programming Language :: Python :: 3
Classifier: Programming Language :: Python :: 3.8
Classifier: Programming Language :: Python :: 3.9
Classifier: Programming Language :: Python :: 3.10
Classifier: Programming Language :: Python :: 3.11
Classifier: Topic :: Scientific/Engineering :: Artificial Intelligence
Classifier: Topic :: Software Development :: Libraries :: Python Modules
Classifier: Operating System :: OS Independent
Requires-Python: >=3.8
License-File: LICENSE
Requires-Dist: numpy>=1.21.0
Requires-Dist: pandas>=1.3.0
Requires-Dist: scikit-learn>=1.0.0
Requires-Dist: matplotlib>=3.4.0
Requires-Dist: seaborn>=0.11.0
Requires-Dist: imbalanced-learn>=0.8.0
Requires-Dist: openpyxl>=3.0.0
Requires-Dist: colorama>=0.4.4
Requires-Dist: plotly>=6.0.1
Provides-Extra: dev
Requires-Dist: pytest>=6.0.0; extra == "dev"
Requires-Dist: black>=21.0.0; extra == "dev"
Requires-Dist: flake8>=3.9.0; extra == "dev"
Dynamic: author
Dynamic: author-email
Dynamic: classifier
Dynamic: description
Dynamic: description-content-type
Dynamic: home-page
Dynamic: keywords
Dynamic: license
Dynamic: license-file
Dynamic: project-url
Dynamic: provides-extra
Dynamic: requires-dist
Dynamic: requires-python
Dynamic: summary
